dbapi2/__init__.py
dbapi2/connection.py
dbapi2/exception.py
dbapi2/utils.py
dbapi2-0.1.1.dist-info/METADATA
dbapi2-0.1.1.dist-info/WHEEL
dbapi2-0.1.1.dist-info/top_level.txt
dbapi2-0.1.1.dist-info/RECORD
