Metadata-Version: 2.4
Name: dbapi2
Version: 0.1.1
Summary: The DBAPI2 for a SQL database engine that operates on CSV files
Author: RND
Requires-Python: >=3.8
Requires-Dist: fastapi==0.115.12
Requires-Dist: pydantic==2.11.1
Requires-Dist: uvicorn[standard]
Requires-Dist: pydantic-settings==2.0.0
Requires-Dist: python-dotenv
Requires-Dist: PyJWT==2.10.1
Requires-Dist: python-multipart
Requires-Dist: PyYAML
Requires-Dist: passlib[bcrypt]>=1.7.4
Requires-Dist: pytest
Requires-Dist: requests
